[
	{
		"bullets": [
			{
				"icon": "fa-university",
				"text": "Your company is very secure"
			},
			{
				"icon": "fa-chevron-right",
				"text": "Your company needs to work on <span class=\"negative\">improving your security</span>"
			},
			{
				"icon": "fa-dollar-sign",
				"text": "We estimate that you could save up to <span class=\"positive\">$12,000</span> if you take more security precautions. We suggest starting that process right now."
			}
		],
		"chart": {
			"title": "chart 1",
			"data": {
				"labels": ["High", "Medium", "Low"],
				"series": [[20, 40, 20], [30, 30, 80]]
			}
		}
	},
	{
		"bullets": [
			{
				"icon": "fa-chevron-left",
				"text": "Your company is not secure"
			},
			{
				"icon": "fa-euro-sign",
				"text": "Your company needs to work on <span class=\"negative\">improving your security</span>"
			},
			{
				"icon": "fa-skull",
				"text": "There are very urgent issues in your system!!!"
			}
		],
		"chart": {
			"title": "chart 2",
			"data": {
				"labels": ["High", "Medium", "Low"],
				"series": [[10, 60, 10], [20, 50, 90]]
			}
		}
	},
	{
		"bullets": [
			{
				"icon": "fa-pallet",
				"text": "<span class=\"positive\">Everything is okay!</span>"
			}
		],
		"chart": {
			"title": "chart 3",
			"data": {
				"labels": ["High", "Medium", "Low"],
				"series": [[40, 60, 20], [15, 10, 60]]
			}
		}
	},
	{
		"bullets": [
			{
				"icon": "fa-cogs",
				"text": "Your company is very secure"
			},
			{
				"icon": "fa-dollar-sign",
				"text": "We estimate that you could save up to <span class=\"positive\">$12,000</span> if you take more security precautions. We suggest starting that process right now."
			}
		],
		"chart": {
			"title": "chart 4",
			"data": {
				"labels": ["High", "Medium", "Low"],
				"series": [[50, 40, 90], [70, 10, 80]]
			}
		}
	}
]
